{
  "ballot_style_mapping": {
    "BS01": { "element_ids": ["element_id_1", "element_id_36", "element_id_37", "element_id_38", "element_id_39"] },
    "BS02": { "element_ids": ["element_id_2", "element_id_3", "element_id_4", "element_id_5", "element_id_6", "element_id_7", "element_id_8", "element_id_9", "element_id_10", "element_id_11", "element_id_12", "element_id_13", "element_id_14", "element_id_15", "element_id_16", "element_id_17", "element_id_18", "element_id_19", "element_id_20"] },
    "BS03": { "element_ids": ["element_id_2", "element_id_3", "element_id_4", "element_id_5", "element_id_6", "element_id_7", "element_id_8", "element_id_9", "element_id_10", "element_id_11", "element_id_12", "element_id_13", "element_id_14", "element_id_15", "element_id_16", "element_id_17", "element_id_18", "element_id_19", "element_id_20", "element_id_46"] },
    "BS04": { "element_ids": ["element_id_21", "element_id_22"] },
    "BS05": { "element_ids": ["element_id_23", "element_id_24"] },
    "BS06": { "element_ids": ["element_id_25", "element_id_40"] },
    "BS07": { "element_ids": ["element_id_26", "element_id_27", "element_id_41"] },
    "BS08": { "element_ids": ["element_id_28", "element_id_42", "element_id_43", "element_id_44", "element_id_66"] },
    "BS09": { "element_ids": ["element_id_28", "element_id_42", "element_id_43", "element_id_44", "element_id_47", "element_id_48", "element_id_49", "element_id_66"] },
    "BS10": { "element_ids": ["element_id_29", "element_id_30", "element_id_31", "element_id_32", "element_id_33"] },
    "BS11": { "element_ids": ["element_id_29", "element_id_30", "element_id_31", "element_id_32", "element_id_33", "element_id_67"] },
    "BS12": { "element_ids": ["element_id_66", "element_id_42", "element_id_43", "element_id_44", "element_id_50", "element_id_51", "element_id_52", "element_id_53", "element_id_54", "element_id_55", "element_id_56", "element_id_57", "element_id_58"] },
    "BS13": { "element_ids": ["element_id_35", "element_id_45"] },
    "BS14": { "element_ids": ["element_id_42", "element_id_43", "element_id_44", "element_id_50", "element_id_51", "element_id_52", "element_id_53", "element_id_54", "element_id_55", "element_id_56", "element_id_57", "element_id_58", "element_id_66"] },
    "BS15": { "element_ids": ["element_id_42", "element_id_43", "element_id_44", "element_id_59", "element_id_66"] },
    "BS16": { "element_ids": ["element_id_60", "element_id_61", "element_id_62", "element_id_63", "element_id_64", "element_id_65"] },
    "BS17": { "element_ids": ["element_id_2", "element_id_3", "element_id_4", "element_id_5", "element_id_6", "element_id_7", "element_id_8", "element_id_9", "element_id_10", "element_id_11", "element_id_12", "element_id_13", "element_id_14", "element_id_15", "element_id_16", "element_id_17", "element_id_18", "element_id_19", "element_id_20", "element_id_60", "element_id_61", "element_id_62", "element_id_63", "element_id_64", "element_id_65"] },
    "BS18": { "element_ids": ["element_id_23", "element_id_24", "element_id_67"] },
    "BS19": { "element_ids": ["element_id_26", "element_id_27", "element_id_41", "element_id_67"] },
    "BS20": { "element_ids": ["element_id_36", "element_id_37", "element_id_38", "element_id_39"] },
    "BS21": { "element_ids": ["element_id_40"] },
    "BS22": { "element_ids": ["element_id_41"] },
    "BS23": { "element_ids": ["element_id_42", "element_id_43", "element_id_44", "element_id_66"] },
    "BS24": { "element_ids": ["element_id_45"] },
    "BS25": { "element_ids": ["element_id_29", "element_id_30", "element_id_31", "element_id_32", "element_id_33", "element_id_46"] },
    "BS26": { "element_ids": ["element_id_2", "element_id_3", "element_id_4", "element_id_5", "element_id_6", "element_id_7", "element_id_8", "element_id_9", "element_id_10", "element_id_11", "element_id_12", "element_id_13", "element_id_14", "element_id_15", "element_id_16", "element_id_17", "element_id_18", "element_id_19", "element_id_20", "element_id_32", "element_id_33"] },
    "BS27": { "element_ids": ["element_id_1", "element_id_21", "element_id_22"] },
    "BS28": { "element_ids": ["element_id_8", "element_id_9", "element_id_23", "element_id_24"] },
    "BS29": { "element_ids": ["element_id_25", "element_id_34"] },
    "BS30": { "element_ids": ["element_id_28", "element_id_42", "element_id_43", "element_id_44", "element_id_50", "element_id_51", "element_id_52", "element_id_53", "element_id_54", "element_id_55", "element_id_56", "element_id_57", "element_id_58"] },
    "BS31": { "element_ids": ["element_id_66", "element_id_67"] },
    "BS32": { "element_ids": ["element_id_47", "element_id_48", "element_id_49"] },
    "BS33": { "element_ids": ["element_id_59", "element_id_60", "element_id_61", "element_id_62", "element_id_63", "element_id_64", "element_id_65"] },
    "BS34": { "element_ids": ["element_id_2", "element_id_3", "element_id_4", "element_id_5", "element_id_26", "element_id_27", "element_id_41"] },
    "BS35": { "element_ids": ["element_id_23", "element_id_24", "element_id_29", "element_id_30", "element_id_31"] }
  }
}